{
    "name": "Dev Protocol",
    "subtitle": "It's Time to Tokenize Open Source Software",
    "description": "👋 Welcome to Dev Protocol&#x27;s docs! Here you can learn about the protocol, token, and how to start using Stakes Social.",
    "footer": "Originally created with ❤ in Japan",
    "url": "https://docs.devprotocol.xyz",
    "githubUrl": "https://github.com/dev-protocol/docs",
    "githubBranch": "main",
    "navigationStyle": "vertical",
    "emoji": "💥",
    "enableSearch": true,
    "enableDarkMode": true,
    "enableEditButton": false,
    "enableDatestamp": true,
    "enableGithubLink": true,
    "enableContact": false,
    "enableNetlifyCMS": false,
    "enableComments": false,
    "enableEncryption": false,
    "enablePageNavigation": true
}