{
  "unversionedId": "Introduction/what-is-devprotocol",
  "id": "version-0.1.0/Introduction/what-is-devprotocol",
  "title": "What is Dev Protocol?",
  "description": "Protocol, Creator tokens, Oracle",
  "source": "@site/versioned_docs/version-0.1.0/Introduction/what-is-devprotocol.md",
  "sourceDirName": "Introduction",
  "slug": "/Introduction/what-is-devprotocol",
  "permalink": "/Introduction/what-is-devprotocol",
  "editUrl": "https://github.com/dev-protocol/docs.devprotocol.xyz/versioned_docs/version-0.1.0/Introduction/what-is-devprotocol.md",
  "tags": [],
  "version": "0.1.0",
  "sidebarPosition": 1,
  "frontMatter": {
    "title": "What is Dev Protocol?",
    "sidebar_position": 1
  },
  "sidebar": "tutorialSidebar",
  "previous": {
    "title": "Introduction",
    "permalink": "/Introduction/"
  },
  "next": {
    "title": "Token Overview",
    "permalink": "/Introduction/devtoken"
  }
}